Workbook

Sheet DashBoard
C7: =SUM(Purchase!I:I) -> 13500 | F7: =SUM(Sales!K:K) -> 2100 | I7: =SUM(Sales!L:L) -> 600 | L7: =SUM(Sales!M:M) -> 1500 | O7: =SUM('Operating Expenses'!F:F) -> 250 | S7: =L7-O7 -> 1250
C14: =SUM(Purchase!G2:G32) -> 20 | F14: =SUM(Sales!I2:I201) -> 2 | I14: =C14-F14 -> 18 | M14: =SUM(Inventory!K2:K16) -> 14400

Sheet Purchase
C1: Date | D1: Purchase Invoice No | E1: Product ID | F1: Product Name | G1: Quantity Purchased | H1: Unit Cost | I1: Total Purchase Cost
C2: 01/07/2026 | D2: PUR001 | E2: =_xlfn.XLOOKUP(Table_Purchases[[#This Row],[Product Name]],Table6[Prodcuts],Table6[Product ID]," ") -> SH001 | F2: Shirt | G2: 20 | H2: 675 | I2: =IF(AND(G2>0,H2>0),G2*H2," ") -> 13500
D3: PUR002 | E3: =_xlfn.XLOOKUP(Table_Purchases[[#This Row],[Product Name]],Table6[Prodcuts],Table6[Product ID]," ") | I3: =IF(AND(G3>0,H3>0),G3*H3," ")
D4: PUR003 | E4: =_xlfn.XLOOKUP(Table_Purchases[[#This Row],[Product Name]],Table6[Prodcuts],Table6[Product ID]," ") | I4: =IF(AND(G4>0,H4>0),G4*H4," ")
D5: PUR004 | E5: =_xlfn.XLOOKUP(Table_Purchases[[#This Row],[Product Name]],Table6[Prodcuts],Table6[Product ID]," ") | I5: =IF(AND(G5>0,H5>0),G5*H5," ")
D6: PUR005 | E6: =_xlfn.XLOOKUP(Table_Purchases[[#This Row],[Product Name]],Table6[Prodcuts],Table6[Product ID]," ") | I6: =IF(AND(G6>0,H6>0),G6*H6," ")
D7: PUR006 | E7: =_xlfn.XLOOKUP(Table_Purchases[[#This Row],[Product Name]],Table6[Prodcuts],Table6[Product ID]," ") | I7: =IF(AND(G7>0,H7>0),G7*H7," ")
D8: PUR007 | E8: =_xlfn.XLOOKUP(Table_Purchases[[#This Row],[Product Name]],Table6[Prodcuts],Table6[Product ID]," ") | I8: =IF(AND(G8>0,H8>0),G8*H8," ")
D9: PUR008 | E9: =_xlfn.XLOOKUP(Table_Purchases[[#This Row],[Product Name]],Table6[Prodcuts],Table6[Product ID]," ") | I9: =IF(AND(G9>0,H9>0),G9*H9," ")
D10: PUR009 | E10: =_xlfn.XLOOKUP(Table_Purchases[[#This Row],[Product Name]],Table6[Prodcuts],Table6[Product ID]," ") | I10: =IF(AND(G10>0,H10>0),G10*H10," ")
D11: PUR010 | E11: =_xlfn.XLOOKUP(Table_Purchases[[#This Row],[Product Name]],Table6[Prodcuts],Table6[Product ID]," ") | I11: =IF(AND(G11>0,H11>0),G11*H11," ")
D12: PUR011 | E12: =_xlfn.XLOOKUP(Table_Purchases[[#This Row],[Product Name]],Table6[Prodcuts],Table6[Product ID]," ") | I12: =IF(AND(G12>0,H12>0),G12*H12," ")
D13: PUR012 | E13: =_xlfn.XLOOKUP(Table_Purchases[[#This Row],[Product Name]],Table6[Prodcuts],Table6[Product ID]," ") | I13: =IF(AND(G13>0,H13>0),G13*H13," ")
D14: PUR013 | E14: =_xlfn.XLOOKUP(Table_Purchases[[#This Row],[Product Name]],Table6[Prodcuts],Table6[Product ID]," ") | I14: =IF(AND(G14>0,H14>0),G14*H14," ")
... D32: PUR031 | E32: =_xlfn.XLOOKUP(Table_Purchases[[#This Row],[Product Name]],Table6[Prodcuts],Table6[Product ID]," ") | I32: =IF(AND(G32>0,H32>0),G32*H32," ")

Sheet Inventory
C1: Product ID | D1: Product Name | E1: Cost Code | F1: Cost Price | G1: Selling Price | H1: Opening Stock | I1: Quantity Sold | J1: Current Inventory | K1: Current InventoryValue
C2: =_xlfn.XLOOKUP(Table_Products[[#This Row],[Product Name]],Table6[Prodcuts],Table6[Product ID]," ") -> SH001 | D2: Shirt | E2: hrr | F2: =IF(Table_Products[[#This Row],[Cost Code]]>" ",VALUE( _xlfn.XLOOKUP(MID(Table_Products[[#This Row],[Cost Code]],1,1),CodeKey[Letter],CodeKey[Number])& _xlfn.XLOOKUP(MID(Table_Products[[#This Row],[Cost Code]],2,1),CodeKey[Letter],CodeKey[Number])& _xlfn.XLOOKUP(MID(Table_Products[[#This Row],[Cost Code]],3,1),CodeKey[Letter],CodeKey[Number]) )," ") -> 300 | G2: =IFERROR(IF(AND(Table_Products[[#This Row],[Cost Price]]>0),Table_Products[[#This Row],[Cost Price]]+(Table_Products[[#This Row],[Cost Price]]*50%)," ")," ") -> 450 | H2: 50 | I2: =IF(SUMIFS(Table_Sales[Quantity Sold],Table_Sales[Product Name],Table_Products[[#This Row],[Product Name]])=0," ",SUMIFS(Table_Sales[Quantity Sold],Table_Sales[Product Name],Table_Products[[#This Row],[Product Name]])) -> 2 | J2: =IFERROR(IF(AND(Table_Products[[#This Row],[Opening Stock]]>0,Table_Products[[#This Row],[Quantity Sold]]>0),Table_Products[[#This Row],[Opening Stock]]-Table_Products[[#This Row],[Quantity Sold]]," ")," ") -> 48 | K2: =IFERROR(IF(AND(Table_Products[[#This Row],[Cost Price]]>0,Table_Products[[#This Row],[Current Inventory]]>0),Table_Products[[#This Row],[Current Inventory]]*Table_Products[[#This Row],[Cost Price]]," ")," ") -> 14400 | S2: Prodcuts | T2: Product ID
C3: =_xlfn.XLOOKUP(Table_Products[[#This Row],[Product Name]],Table6[Prodcuts],Table6[Product ID]," ") | F3: =IF(Table_Products[[#This Row],[Cost Code]]>" ",VALUE( _xlfn.XLOOKUP(MID(Table_Products[[#This Row],[Cost Code]],1,1),CodeKey[Letter],CodeKey[Number])& _xlfn.XLOOKUP(MID(Table_Products[[#This Row],[Cost Code]],2,1),CodeKey[Letter],CodeKey[Number])& _xlfn.XLOOKUP(MID(Table_Products[[#This Row],[Cost Code]],3,1),CodeKey[Letter],CodeKey[Number]) )," ") | G3: =IFERROR(IF(AND(Table_Products[[#This Row],[Cost Price]]>0),Table_Products[[#This Row],[Cost Price]]+(Table_Products[[#This Row],[Cost Price]]*50%)," ")," ") | I3: =IF(SUMIFS(Table_Sales[Quantity Sold],Table_Sales[Product Name],Table_Products[[#This Row],[Product Name]])=0," ",SUMIFS(Table_Sales[Quantity Sold],Table_Sales[Product Name],Table_Products[[#This Row],[Product Name]])) | J3: =IFERROR(IF(AND(Table_Products[[#This Row],[Opening Stock]]>0,Table_Products[[#This Row],[Quantity Sold]]>0),Table_Products[[#This Row],[Opening Stock]]-Table_Products[[#This Row],[Quantity Sold]]," ")," ") | K3: =IFERROR(IF(AND(Table_Products[[#This Row],[Cost Price]]>0,Table_Products[[#This Row],[Current Inventory]]>0),Table_Products[[#This Row],[Current Inventory]]*Table_Products[[#This Row],[Cost Price]]," ")," ") | S3: Shirt | T3: SH001
C4: =_xlfn.XLOOKUP(Table_Products[[#This Row],[Product Name]],Table6[Prodcuts],Table6[Product ID]," ") | F4: =IF(Table_Products[[#This Row],[Cost Code]]>" ",VALUE( _xlfn.XLOOKUP(MID(Table_Products[[#This Row],[Cost Code]],1,1),CodeKey[Letter],CodeKey[Number])& _xlfn.XLOOKUP(MID(Table_Products[[#This Row],[Cost Code]],2,1),CodeKey[Letter],CodeKey[Number])& _xlfn.XLOOKUP(MID(Table_Products[[#This Row],[Cost Code]],3,1),CodeKey[Letter],CodeKey[Number]) )," ") | G4: =IFERROR(IF(AND(Table_Products[[#This Row],[Cost Price]]>0),Table_Products[[#This Row],[Cost Price]]+(Table_Products[[#This Row],[Cost Price]]*50%)," ")," ") | I4: =IF(SUMIFS(Table_Sales[Quantity Sold],Table_Sales[Product Name],Table_Products[[#This Row],[Product Name]])=0," ",SUMIFS(Table_Sales[Quantity Sold],Table_Sales[Product Name],Table_Products[[#This Row],[Product Name]])) | J4: =IFERROR(IF(AND(Table_Products[[#This Row],[Opening Stock]]>0,Table_Products[[#This Row],[Quantity Sold]]>0),Table_Products[[#This Row],[Opening Stock]]-Table_Products[[#This Row],[Quantity Sold]]," ")," ") | K4: =IFERROR(IF(AND(Table_Products[[#This Row],[Cost Price]]>0,Table_Products[[#This Row],[Current Inventory]]>0),Table_Products[[#This Row],[Current Inventory]]*Table_Products[[#This Row],[Cost Price]]," ")," ") | S4: Drop Shoulder | T4: DS001
C5: =_xlfn.XLOOKUP(Table_Products[[#This Row],[Product Name]],Table6[Prodcuts],Table6[Product ID]," ") | F5: =IF(Table_Products[[#This Row],[Cost Code]]>" ",VALUE( _xlfn.XLOOKUP(MID(Table_Products[[#This Row],[Cost Code]],1,1),CodeKey[Letter],CodeKey[Number])& _xlfn.XLOOKUP(MID(Table_Products[[#This Row],[Cost Code]],2,1),CodeKey[Letter],CodeKey[Number])& _xlfn.XLOOKUP(MID(Table_Products[[#This Row],[Cost Code]],3,1),CodeKey[Letter],CodeKey[Number]) )," ") | G5: =IFERROR(IF(AND(Table_Products[[#This Row],[Cost Price]]>0),Table_Products[[#This Row],[Cost Price]]+(Table_Products[[#This Row],[Cost Price]]*50%)," ")," ") | I5: =IF(SUMIFS(Table_Sales[Quantity Sold],Table_Sales[Product Name],Table_Products[[#This Row],[Product Name]])=0," ",SUMIFS(Table_Sales[Quantity Sold],Table_Sales[Product Name],Table_Products[[#This Row],[Product Name]])) | J5: =IFERROR(IF(AND(Table_Products[[#This Row],[Opening Stock]]>0,Table_Products[[#This Row],[Quantity Sold]]>0),Table_Products[[#This Row],[Opening Stock]]-Table_Products[[#This Row],[Quantity Sold]]," ")," ") | K5: =IFERROR(IF(AND(Table_Products[[#This Row],[Cost Price]]>0,Table_Products[[#This Row],[Current Inventory]]>0),Table_Products[[#This Row],[Current Inventory]]*Table_Products[[#This Row],[Cost Price]]," ")," ") | S5: T-Shirt | T5: TS001
C6: =_xlfn.XLOOKUP(Table_Products[[#This Row],[Product Name]],Table6[Prodcuts],Table6[Product ID]," ") | F6: =IF(Table_Products[[#This Row],[Cost Code]]>" ",VALUE( _xlfn.XLOOKUP(MID(Table_Products[[#This Row],[Cost Code]],1,1),CodeKey[Letter],CodeKey[Number])& _xlfn.XLOOKUP(MID(Table_Products[[#This Row],[Cost Code]],2,1),CodeKey[Letter],CodeKey[Number])& _xlfn.XLOOKUP(MID(Table_Products[[#This Row],[Cost Code]],3,1),CodeKey[Letter],CodeKey[Number]) )," ") | G6: =IFERROR(IF(AND(Table_Products[[#This Row],[Cost Price]]>0),Table_Products[[#This Row],[Cost Price]]+(Table_Products[[#This Row],[Cost Price]]*50%)," ")," ") | I6: =IF(SUMIFS(Table_Sales[Quantity Sold],Table_Sales[Product Name],Table_Products[[#This Row],[Product Name]])=0," ",SUMIFS(Table_Sales[Quantity Sold],Table_Sales[Product Name],Table_Products[[#This Row],[Product Name]])) | J6: =IFERROR(IF(AND(Table_Products[[#This Row],[Opening Stock]]>0,Table_Products[[#This Row],[Quantity Sold]]>0),Table_Products[[#This Row],[Opening Stock]]-Table_Products[[#This Row],[Quantity Sold]]," ")," ") | K6: =IFERROR(IF(AND(Table_Products[[#This Row],[Cost Price]]>0,Table_Products[[#This Row],[Current Inventory]]>0),Table_Products[[#This Row],[Current Inventory]]*Table_Products[[#This Row],[Cost Price]]," ")," ") | S6: Polo T-Shirt | T6: PS001
C7: =_xlfn.XLOOKUP(Table_Products[[#This Row],[Product Name]],Table6[Prodcuts],Table6[Product ID]," ") | F7: =IF(Table_Products[[#This Row],[Cost Code]]>" ",VALUE( _xlfn.XLOOKUP(MID(Table_Products[[#This Row],[Cost Code]],1,1),CodeKey[Letter],CodeKey[Number])& _xlfn.XLOOKUP(MID(Table_Products[[#This Row],[Cost Code]],2,1),CodeKey[Letter],CodeKey[Number])& _xlfn.XLOOKUP(MID(Table_Products[[#This Row],[Cost Code]],3,1),CodeKey[Letter],CodeKey[Number]) )," ") | G7: =IFERROR(IF(AND(Table_Products[[#This Row],[Cost Price]]>0),Table_Products[[#This Row],[Cost Price]]+(Table_Products[[#This Row],[Cost Price]]*50%)," ")," ") | I7: =IF(SUMIFS(Table_Sales[Quantity Sold],Table_Sales[Product Name],Table_Products[[#This Row],[Product Name]])=0," ",SUMIFS(Table_Sales[Quantity Sold],Table_Sales[Product Name],Table_Products[[#This Row],[Product Name]])) | J7: =IFERROR(IF(AND(Table_Products[[#This Row],[Opening Stock]]>0,Table_Products[[#This Row],[Quantity Sold]]>0),Table_Products[[#This Row],[Opening Stock]]-Table_Products[[#This Row],[Quantity Sold]]," ")," ") | K7: =IFERROR(IF(AND(Table_Products[[#This Row],[Cost Price]]>0,Table_Products[[#This Row],[Current Inventory]]>0),Table_Products[[#This Row],[Current Inventory]]*Table_Products[[#This Row],[Cost Price]]," ")," ") | S7: Baggy Pant | T7: BP001
C8: =_xlfn.XLOOKUP(Table_Products[[#This Row],[Product Name]],Table6[Prodcuts],Table6[Product ID]," ") | F8: =IF(Table_Products[[#This Row],[Cost Code]]>" ",VALUE( _xlfn.XLOOKUP(MID(Table_Products[[#This Row],[Cost Code]],1,1),CodeKey[Letter],CodeKey[Number])& _xlfn.XLOOKUP(MID(Table_Products[[#This Row],[Cost Code]],2,1),CodeKey[Letter],CodeKey[Number])& _xlfn.XLOOKUP(MID(Table_Products[[#This Row],[Cost Code]],3,1),CodeKey[Letter],CodeKey[Number]) )," ") | G8: =IFERROR(IF(AND(Table_Products[[#This Row],[Cost Price]]>0),Table_Products[[#This Row],[Cost Price]]+(Table_Products[[#This Row],[Cost Price]]*50%)," ")," ") | I8: =IF(SUMIFS(Table_Sales[Quantity Sold],Table_Sales[Product Name],Table_Products[[#This Row],[Product Name]])=0," ",SUMIFS(Table_Sales[Quantity Sold],Table_Sales[Product Name],Table_Products[[#This Row],[Product Name]])) | J8: =IFERROR(IF(AND(Table_Products[[#This Row],[Opening Stock]]>0,Table_Products[[#This Row],[Quantity Sold]]>0),Table_Products[[#This Row],[Opening Stock]]-Table_Products[[#This Row],[Quantity Sold]]," ")," ") | K8: =IFERROR(IF(AND(Table_Products[[#This Row],[Cost Price]]>0,Table_Products[[#This Row],[Current Inventory]]>0),Table_Products[[#This Row],[Current Inventory]]*Table_Products[[#This Row],[Cost Price]]," ")," ") | S8: Gabading Pant | T8: GP001
C9: =_xlfn.XLOOKUP(Table_Products[[#This Row],[Product Name]],Table6[Prodcuts],Table6[Product ID]," ") | F9: =IF(Table_Products[[#This Row],[Cost Code]]>" ",VALUE( _xlfn.XLOOKUP(MID(Table_Products[[#This Row],[Cost Code]],1,1),CodeKey[Letter],CodeKey[Number])& _xlfn.XLOOKUP(MID(Table_Products[[#This Row],[Cost Code]],2,1),CodeKey[Letter],CodeKey[Number])& _xlfn.XLOOKUP(MID(Table_Products[[#This Row],[Cost Code]],3,1),CodeKey[Letter],CodeKey[Number]) )," ") | G9: =IFERROR(IF(AND(Table_Products[[#This Row],[Cost Price]]>0),Table_Products[[#This Row],[Cost Price]]+(Table_Products[[#This Row],[Cost Price]]*50%)," ")," ") | I9: =IF(SUMIFS(Table_Sales[Quantity Sold],Table_Sales[Product Name],Table_Products[[#This Row],[Product Name]])=0," ",SUMIFS(Table_Sales[Quantity Sold],Table_Sales[Product Name],Table_Products[[#This Row],[Product Name]])) | J9: =IFERROR(IF(AND(Table_Products[[#This Row],[Opening Stock]]>0,Table_Products[[#This Row],[Quantity Sold]]>0),Table_Products[[#This Row],[Opening Stock]]-Table_Products[[#This Row],[Quantity Sold]]," ")," ") | K9: =IFERROR(IF(AND(Table_Products[[#This Row],[Cost Price]]>0,Table_Products[[#This Row],[Current Inventory]]>0),Table_Products[[#This Row],[Current Inventory]]*Table_Products[[#This Row],[Cost Price]]," ")," ") | S9: Jeans Pant | T9: JP001
C10: =_xlfn.XLOOKUP(Table_Products[[#This Row],[Product Name]],Table6[Prodcuts],Table6[Product ID]," ") | F10: =IF(Table_Products[[#This Row],[Cost Code]]>" ",VALUE( _xlfn.XLOOKUP(MID(Table_Products[[#This Row],[Cost Code]],1,1),CodeKey[Letter],CodeKey[Number])& _xlfn.XLOOKUP(MID(Table_Products[[#This Row],[Cost Code]],2,1),CodeKey[Letter],CodeKey[Number])& _xlfn.XLOOKUP(MID(Table_Products[[#This Row],[Cost Code]],3,1),CodeKey[Letter],CodeKey[Number]) )," ") | G10: =IFERROR(IF(AND(Table_Products[[#This Row],[Cost Price]]>0),Table_Products[[#This Row],[Cost Price]]+(Table_Products[[#This Row],[Cost Price]]*50%)," ")," ") | I10: =IF(SUMIFS(Table_Sales[Quantity Sold],Table_Sales[Product Name],Table_Products[[#This Row],[Product Name]])=0," ",SUMIFS(Table_Sales[Quantity Sold],Table_Sales[Product Name],Table_Products[[#This Row],[Product Name]])) | J10: =IFERROR(IF(AND(Table_Products[[#This Row],[Opening Stock]]>0,Table_Products[[#This Row],[Quantity Sold]]>0),Table_Products[[#This Row],[Opening Stock]]-Table_Products[[#This Row],[Quantity Sold]]," ")," ") | K10: =IFERROR(IF(AND(Table_Products[[#This Row],[Cost Price]]>0,Table_Products[[#This Row],[Current Inventory]]>0),Table_Products[[#This Row],[Current Inventory]]*Table_Products[[#This Row],[Cost Price]]," ")," ") | S10: Panjabi | T10: PJ001
C11: =_xlfn.XLOOKUP(Table_Products[[#This Row],[Product Name]],Table6[Prodcuts],Table6[Product ID]," ") | F11: =IF(Table_Products[[#This Row],[Cost Code]]>" ",VALUE( _xlfn.XLOOKUP(MID(Table_Products[[#This Row],[Cost Code]],1,1),CodeKey[Letter],CodeKey[Number])& _xlfn.XLOOKUP(MID(Table_Products[[#This Row],[Cost Code]],2,1),CodeKey[Letter],CodeKey[Number])& _xlfn.XLOOKUP(MID(Table_Products[[#This Row],[Cost Code]],3,1),CodeKey[Letter],CodeKey[Number]) )," ") | G11: =IFERROR(IF(AND(Table_Products[[#This Row],[Cost Price]]>0),Table_Products[[#This Row],[Cost Price]]+(Table_Products[[#This Row],[Cost Price]]*50%)," ")," ") | I11: =IF(SUMIFS(Table_Sales[Quantity Sold],Table_Sales[Product Name],Table_Products[[#This Row],[Product Name]])=0," ",SUMIFS(Table_Sales[Quantity Sold],Table_Sales[Product Name],Table_Products[[#This Row],[Product Name]])) | J11: =IFERROR(IF(AND(Table_Products[[#This Row],[Opening Stock]]>0,Table_Products[[#This Row],[Quantity Sold]]>0),Table_Products[[#This Row],[Opening Stock]]-Table_Products[[#This Row],[Quantity Sold]]," ")," ") | K11: =IFERROR(IF(AND(Table_Products[[#This Row],[Cost Price]]>0,Table_Products[[#This Row],[Current Inventory]]>0),Table_Products[[#This Row],[Current Inventory]]*Table_Products[[#This Row],[Cost Price]]," ")," ") | S11: Jersey | T11: JR001
C12: =_xlfn.XLOOKUP(Table_Products[[#This Row],[Product Name]],Table6[Prodcuts],Table6[Product ID]," ") | G12: =IFERROR(IF(AND(Table_Products[[#This Row],[Cost Price]]>0),Table_Products[[#This Row],[Cost Price]]+(Table_Products[[#This Row],[Cost Price]]*50%)," ")," ") | I12: =IF(SUMIFS(Table_Sales[Quantity Sold],Table_Sales[Product Name],Table_Products[[#This Row],[Product Name]])=0," ",SUMIFS(Table_Sales[Quantity Sold],Table_Sales[Product Name],Table_Products[[#This Row],[Product Name]])) | J12: =IFERROR(IF(AND(Table_Products[[#This Row],[Opening Stock]]>0,Table_Products[[#This Row],[Quantity Sold]]>0),Table_Products[[#This Row],[Opening Stock]]-Table_Products[[#This Row],[Quantity Sold]]," ")," ") | K12: =IFERROR(IF(AND(Table_Products[[#This Row],[Cost Price]]>0,Table_Products[[#This Row],[Current Inventory]]>0),Table_Products[[#This Row],[Current Inventory]]*Table_Products[[#This Row],[Cost Price]]," ")," ") | S12: Others | T12: OT001
C13: =_xlfn.XLOOKUP(Table_Products[[#This Row],[Product Name]],Table6[Prodcuts],Table6[Product ID]," ") | F13: =IF(Table_Products[[#This Row],[Cost Code]]>" ",VALUE( _xlfn.XLOOKUP(MID(Table_Products[[#This Row],[Cost Code]],1,1),'CodeKey'!C:C,'CodeKey'!D:D)& _xlfn.XLOOKUP(MID(Table_Products[[#This Row],[Cost Code]],2,1),'CodeKey'!C:C,'CodeKey'!D:D)& _xlfn.XLOOKUP(MID(Table_Products[[#This Row],[Cost Code]],3,1),'CodeKey'!C:C,'CodeKey'!D:D) )," ") | G13: =IFERROR(IF(AND(Table_Products[[#This Row],[Cost Price]]>0),Table_Products[[#This Row],[Cost Price]]+(Table_Products[[#This Row],[Cost Price]]*50%)," ")," ") | I13: =IF(SUMIFS(Table_Sales[Quantity Sold],Table_Sales[Product Name],Table_Products[[#This Row],[Product Name]])=0," ",SUMIFS(Table_Sales[Quantity Sold],Table_Sales[Product Name],Table_Products[[#This Row],[Product Name]])) | J13: =IFERROR(IF(AND(Table_Products[[#This Row],[Opening Stock]]>0,Table_Products[[#This Row],[Quantity Sold]]>0),Table_Products[[#This Row],[Opening Stock]]-Table_Products[[#This Row],[Quantity Sold]]," ")," ") | K13: =IFERROR(IF(AND(Table_Products[[#This Row],[Cost Price]]>0,Table_Products[[#This Row],[Current Inventory]]>0),Table_Products[[#This Row],[Current Inventory]]*Table_Products[[#This Row],[Cost Price]]," ")," ")
C14: =_xlfn.XLOOKUP(Table_Products[[#This Row],[Product Name]],Table6[Prodcuts],Table6[Product ID]," ") | F14: =IF(Table_Products[[#This Row],[Cost Code]]>" ",VALUE( _xlfn.XLOOKUP(MID(Table_Products[[#This Row],[Cost Code]],1,1),'CodeKey'!C:C,'CodeKey'!D:D)& _xlfn.XLOOKUP(MID(Table_Products[[#This Row],[Cost Code]],2,1),'CodeKey'!C:C,'CodeKey'!D:D)& _xlfn.XLOOKUP(MID(Table_Products[[#This Row],[Cost Code]],3,1),'CodeKey'!C:C,'CodeKey'!D:D) )," ") | G14: =IFERROR(IF(AND(Table_Products[[#This Row],[Cost Price]]>0),Table_Products[[#This Row],[Cost Price]]+(Table_Products[[#This Row],[Cost Price]]*50%)," ")," ") | I14: =IF(SUMIFS(Table_Sales[Quantity Sold],Table_Sales[Product Name],Table_Products[[#This Row],[Product Name]])=0," ",SUMIFS(Table_Sales[Quantity Sold],Table_Sales[Product Name],Table_Products[[#This Row],[Product Name]])) | J14: =IFERROR(IF(AND(Table_Products[[#This Row],[Opening Stock]]>0,Table_Products[[#This Row],[Quantity Sold]]>0),Table_Products[[#This Row],[Opening Stock]]-Table_Products[[#This Row],[Quantity Sold]]," ")," ") | K14: =IFERROR(IF(AND(Table_Products[[#This Row],[Cost Price]]>0,Table_Products[[#This Row],[Current Inventory]]>0),Table_Products[[#This Row],[Current Inventory]]*Table_Products[[#This Row],[Cost Price]]," ")," ")
C15: =_xlfn.XLOOKUP(Table_Products[[#This Row],[Product Name]],Table6[Prodcuts],Table6[Product ID]," ") | F15: =IF(Table_Products[[#This Row],[Cost Code]]>" ",VALUE( _xlfn.XLOOKUP(MID(Table_Products[[#This Row],[Cost Code]],1,1),'CodeKey'!C:C,'CodeKey'!D:D)& _xlfn.XLOOKUP(MID(Table_Products[[#This Row],[Cost Code]],2,1),'CodeKey'!C:C,'CodeKey'!D:D)& _xlfn.XLOOKUP(MID(Table_Products[[#This Row],[Cost Code]],3,1),'CodeKey'!C:C,'CodeKey'!D:D) )," ") | G15: =IFERROR(IF(AND(Table_Products[[#This Row],[Cost Price]]>0),Table_Products[[#This Row],[Cost Price]]+(Table_Products[[#This Row],[Cost Price]]*50%)," ")," ") | I15: =IF(SUMIFS(Table_Sales[Quantity Sold],Table_Sales[Product Name],Table_Products[[#This Row],[Product Name]])=0," ",SUMIFS(Table_Sales[Quantity Sold],Table_Sales[Product Name],Table_Products[[#This Row],[Product Name]])) | J15: =IFERROR(IF(AND(Table_Products[[#This Row],[Opening Stock]]>0,Table_Products[[#This Row],[Quantity Sold]]>0),Table_Products[[#This Row],[Opening Stock]]-Table_Products[[#This Row],[Quantity Sold]]," ")," ") | K15: =IFERROR(IF(AND(Table_Products[[#This Row],[Cost Price]]>0,Table_Products[[#This Row],[Current Inventory]]>0),Table_Products[[#This Row],[Current Inventory]]*Table_Products[[#This Row],[Cost Price]]," ")," ")
C16: =_xlfn.XLOOKUP(Table_Products[[#This Row],[Product Name]],Table6[Prodcuts],Table6[Product ID]," ") | F16: =IF(Table_Products[[#This Row],[Cost Code]]>" ",VALUE( _xlfn.XLOOKUP(MID(Table_Products[[#This Row],[Cost Code]],1,1),'CodeKey'!C:C,'CodeKey'!D:D)& _xlfn.XLOOKUP(MID(Table_Products[[#This Row],[Cost Code]],2,1),'CodeKey'!C:C,'CodeKey'!D:D)& _xlfn.XLOOKUP(MID(Table_Products[[#This Row],[Cost Code]],3,1),'CodeKey'!C:C,'CodeKey'!D:D) )," ") | G16: =IFERROR(IF(AND(Table_Products[[#This Row],[Cost Price]]>0),Table_Products[[#This Row],[Cost Price]]+(Table_Products[[#This Row],[Cost Price]]*50%)," ")," ") | I16: =IF(SUMIFS(Table_Sales[Quantity Sold],Table_Sales[Product Name],Table_Products[[#This Row],[Product Name]])=0," ",SUMIFS(Table_Sales[Quantity Sold],Table_Sales[Product Name],Table_Products[[#This Row],[Product Name]])) | J16: =IFERROR(IF(AND(Table_Products[[#This Row],[Opening Stock]]>0,Table_Products[[#This Row],[Quantity Sold]]>0),Table_Products[[#This Row],[Opening Stock]]-Table_Products[[#This Row],[Quantity Sold]]," ")," ") | K16: =IFERROR(IF(AND(Table_Products[[#This Row],[Cost Price]]>0,Table_Products[[#This Row],[Current Inventory]]>0),Table_Products[[#This Row],[Current Inventory]]*Table_Products[[#This Row],[Cost Price]]," ")," ")

Sheet Sales
C1: Date | D1: Sales Invoice No | E1: Customer Name | F1: Phone Number | G1: Product ID | H1: Product Name | I1: Quantity Sold | J1: Selling Price | K1: Revenue | L1: Cost of Goods Sold | M1: Gross Profit
C2: 46149 | D2: INV001 | E2: Rahim | F2: 017XXXXXXXX | G2: =_xlfn.XLOOKUP(Table_Sales[[#This Row],[Product Name]],Table6[Prodcuts],Table6[Product ID]," ") -> SH001 | H2: Shirt | I2: 2 | J2: 1050 | K2: =IF(AND(Table_Sales[[#This Row],[Quantity Sold]]>0,Table_Sales[[#This Row],[Selling Price]]>0),Table_Sales[[#This Row],[Quantity Sold]]*Table_Sales[[#This Row],[Selling Price]]," ") -> 2100 | L2: =IF(AND(Table_Sales[[#This Row],[Quantity Sold]]>0,_xlfn.XLOOKUP(Table_Sales[[#This Row],[Product Name]],Inventory!D:D,Inventory!F:F)>0),I2*_xlfn.XLOOKUP(Table_Sales[[#This Row],[Product Name]],Inventory!D:D,Inventory!F:F)," ") -> 600 | M2: =IFERROR( IF(AND(Table_Sales[[#This Row],[Revenue]]>0,Table_Sales[[#This Row],[Cost of Goods Sold]]>0), Table_Sales[[#This Row],[Revenue]]-Table_Sales[[#This Row],[Cost of Goods Sold]], ""), "") -> 1500
D3: INV002 | G3: =_xlfn.XLOOKUP(Table_Sales[[#This Row],[Product Name]],Table6[Prodcuts],Table6[Product ID]," ") | K3: =IF(AND(Table_Sales[[#This Row],[Quantity Sold]]>0,Table_Sales[[#This Row],[Selling Price]]>0),Table_Sales[[#This Row],[Quantity Sold]]*Table_Sales[[#This Row],[Selling Price]]," ") | L3: =IF(AND(Table_Sales[[#This Row],[Quantity Sold]]>0,_xlfn.XLOOKUP(Table_Sales[[#This Row],[Product Name]],Inventory!D:D,Inventory!F:F)>0),I3*_xlfn.XLOOKUP(Table_Sales[[#This Row],[Product Name]],Inventory!D:D,Inventory!F:F)," ") | M3: =IFERROR( IF(AND(Table_Sales[[#This Row],[Revenue]]>0,Table_Sales[[#This Row],[Cost of Goods Sold]]>0), Table_Sales[[#This Row],[Revenue]]-Table_Sales[[#This Row],[Cost of Goods Sold]], ""), "")
D4: INV003 | G4: =_xlfn.XLOOKUP(Table_Sales[[#This Row],[Product Name]],Table6[Prodcuts],Table6[Product ID]," ") | K4: =IF(AND(Table_Sales[[#This Row],[Quantity Sold]]>0,Table_Sales[[#This Row],[Selling Price]]>0),Table_Sales[[#This Row],[Quantity Sold]]*Table_Sales[[#This Row],[Selling Price]]," ") | L4: =IF(AND(Table_Sales[[#This Row],[Quantity Sold]]>0,_xlfn.XLOOKUP(Table_Sales[[#This Row],[Product Name]],Inventory!D:D,Inventory!F:F)>0),I4*_xlfn.XLOOKUP(Table_Sales[[#This Row],[Product Name]],Inventory!D:D,Inventory!F:F)," ") | M4: =IFERROR( IF(AND(Table_Sales[[#This Row],[Revenue]]>0,Table_Sales[[#This Row],[Cost of Goods Sold]]>0), Table_Sales[[#This Row],[Revenue]]-Table_Sales[[#This Row],[Cost of Goods Sold]], ""), "")
D5: INV004 | G5: =_xlfn.XLOOKUP(Table_Sales[[#This Row],[Product Name]],Table6[Prodcuts],Table6[Product ID]," ") | K5: =IF(AND(Table_Sales[[#This Row],[Quantity Sold]]>0,Table_Sales[[#This Row],[Selling Price]]>0),Table_Sales[[#This Row],[Quantity Sold]]*Table_Sales[[#This Row],[Selling Price]]," ") | L5: =IF(AND(Table_Sales[[#This Row],[Quantity Sold]]>0,_xlfn.XLOOKUP(Table_Sales[[#This Row],[Product Name]],Inventory!D:D,Inventory!F:F)>0),I5*_xlfn.XLOOKUP(Table_Sales[[#This Row],[Product Name]],Inventory!D:D,Inventory!F:F)," ") | M5: =IFERROR( IF(AND(Table_Sales[[#This Row],[Revenue]]>0,Table_Sales[[#This Row],[Cost of Goods Sold]]>0), Table_Sales[[#This Row],[Revenue]]-Table_Sales[[#This Row],[Cost of Goods Sold]], ""), "")
D6: INV005 | G6: =_xlfn.XLOOKUP(Table_Sales[[#This Row],[Product Name]],Table6[Prodcuts],Table6[Product ID]," ") | K6: =IF(AND(Table_Sales[[#This Row],[Quantity Sold]]>0,Table_Sales[[#This Row],[Selling Price]]>0),Table_Sales[[#This Row],[Quantity Sold]]*Table_Sales[[#This Row],[Selling Price]]," ") | L6: =IF(AND(Table_Sales[[#This Row],[Quantity Sold]]>0,_xlfn.XLOOKUP(Table_Sales[[#This Row],[Product Name]],Inventory!D:D,Inventory!F:F)>0),I6*_xlfn.XLOOKUP(Table_Sales[[#This Row],[Product Name]],Inventory!D:D,Inventory!F:F)," ") | M6: =IFERROR( IF(AND(Table_Sales[[#This Row],[Revenue]]>0,Table_Sales[[#This Row],[Cost of Goods Sold]]>0), Table_Sales[[#This Row],[Revenue]]-Table_Sales[[#This Row],[Cost of Goods Sold]], ""), "")
D7: INV006 | G7: =_xlfn.XLOOKUP(Table_Sales[[#This Row],[Product Name]],Table6[Prodcuts],Table6[Product ID]," ") | K7: =IF(AND(Table_Sales[[#This Row],[Quantity Sold]]>0,Table_Sales[[#This Row],[Selling Price]]>0),Table_Sales[[#This Row],[Quantity Sold]]*Table_Sales[[#This Row],[Selling Price]]," ") | L7: =IF(AND(Table_Sales[[#This Row],[Quantity Sold]]>0,_xlfn.XLOOKUP(Table_Sales[[#This Row],[Product Name]],Inventory!D:D,Inventory!F:F)>0),I7*_xlfn.XLOOKUP(Table_Sales[[#This Row],[Product Name]],Inventory!D:D,Inventory!F:F)," ") | M7: =IFERROR( IF(AND(Table_Sales[[#This Row],[Revenue]]>0,Table_Sales[[#This Row],[Cost of Goods Sold]]>0), Table_Sales[[#This Row],[Revenue]]-Table_Sales[[#This Row],[Cost of Goods Sold]], ""), "")
D8: INV007 | G8: =_xlfn.XLOOKUP(Table_Sales[[#This Row],[Product Name]],Table6[Prodcuts],Table6[Product ID]," ") | K8: =IF(AND(Table_Sales[[#This Row],[Quantity Sold]]>0,Table_Sales[[#This Row],[Selling Price]]>0),Table_Sales[[#This Row],[Quantity Sold]]*Table_Sales[[#This Row],[Selling Price]]," ") | L8: =IF(AND(Table_Sales[[#This Row],[Quantity Sold]]>0,_xlfn.XLOOKUP(Table_Sales[[#This Row],[Product Name]],Inventory!D:D,Inventory!F:F)>0),I8*_xlfn.XLOOKUP(Table_Sales[[#This Row],[Product Name]],Inventory!D:D,Inventory!F:F)," ") | M8: =IFERROR( IF(AND(Table_Sales[[#This Row],[Revenue]]>0,Table_Sales[[#This Row],[Cost of Goods Sold]]>0), Table_Sales[[#This Row],[Revenue]]-Table_Sales[[#This Row],[Cost of Goods Sold]], ""), "")
D9: INV008 | G9: =_xlfn.XLOOKUP(Table_Sales[[#This Row],[Product Name]],Table6[Prodcuts],Table6[Product ID]," ") | K9: =IF(AND(Table_Sales[[#This Row],[Quantity Sold]]>0,Table_Sales[[#This Row],[Selling Price]]>0),Table_Sales[[#This Row],[Quantity Sold]]*Table_Sales[[#This Row],[Selling Price]]," ") | L9: =IF(AND(Table_Sales[[#This Row],[Quantity Sold]]>0,_xlfn.XLOOKUP(Table_Sales[[#This Row],[Product Name]],Inventory!D:D,Inventory!F:F)>0),I9*_xlfn.XLOOKUP(Table_Sales[[#This Row],[Product Name]],Inventory!D:D,Inventory!F:F)," ") | M9: =IFERROR( IF(AND(Table_Sales[[#This Row],[Revenue]]>0,Table_Sales[[#This Row],[Cost of Goods Sold]]>0), Table_Sales[[#This Row],[Revenue]]-Table_Sales[[#This Row],[Cost of Goods Sold]], ""), "")
D10: INV009 | G10: =_xlfn.XLOOKUP(Table_Sales[[#This Row],[Product Name]],Table6[Prodcuts],Table6[Product ID]," ") | K10: =IF(AND(Table_Sales[[#This Row],[Quantity Sold]]>0,Table_Sales[[#This Row],[Selling Price]]>0),Table_Sales[[#This Row],[Quantity Sold]]*Table_Sales[[#This Row],[Selling Price]]," ") | L10: =IF(AND(Table_Sales[[#This Row],[Quantity Sold]]>0,_xlfn.XLOOKUP(Table_Sales[[#This Row],[Product Name]],Inventory!D:D,Inventory!F:F)>0),I10*_xlfn.XLOOKUP(Table_Sales[[#This Row],[Product Name]],Inventory!D:D,Inventory!F:F)," ") | M10: =IFERROR( IF(AND(Table_Sales[[#This Row],[Revenue]]>0,Table_Sales[[#This Row],[Cost of Goods Sold]]>0), Table_Sales[[#This Row],[Revenue]]-Table_Sales[[#This Row],[Cost of Goods Sold]], ""), "")
D11: INV010 | G11: =_xlfn.XLOOKUP(Table_Sales[[#This Row],[Product Name]],Table6[Prodcuts],Table6[Product ID]," ") | K11: =IF(AND(Table_Sales[[#This Row],[Quantity Sold]]>0,Table_Sales[[#This Row],[Selling Price]]>0),Table_Sales[[#This Row],[Quantity Sold]]*Table_Sales[[#This Row],[Selling Price]]," ") | L11: =IF(AND(Table_Sales[[#This Row],[Quantity Sold]]>0,_xlfn.XLOOKUP(Table_Sales[[#This Row],[Product Name]],Inventory!D:D,Inventory!F:F)>0),I11*_xlfn.XLOOKUP(Table_Sales[[#This Row],[Product Name]],Inventory!D:D,Inventory!F:F)," ") | M11: =IFERROR( IF(AND(Table_Sales[[#This Row],[Revenue]]>0,Table_Sales[[#This Row],[Cost of Goods Sold]]>0), Table_Sales[[#This Row],[Revenue]]-Table_Sales[[#This Row],[Cost of Goods Sold]], ""), "")
D12: INV011 | G12: =_xlfn.XLOOKUP(Table_Sales[[#This Row],[Product Name]],Table6[Prodcuts],Table6[Product ID]," ") | K12: =IF(AND(Table_Sales[[#This Row],[Quantity Sold]]>0,Table_Sales[[#This Row],[Selling Price]]>0),Table_Sales[[#This Row],[Quantity Sold]]*Table_Sales[[#This Row],[Selling Price]]," ") | L12: =IF(AND(Table_Sales[[#This Row],[Quantity Sold]]>0,_xlfn.XLOOKUP(Table_Sales[[#This Row],[Product Name]],Inventory!D:D,Inventory!F:F)>0),I12*_xlfn.XLOOKUP(Table_Sales[[#This Row],[Product Name]],Inventory!D:D,Inventory!F:F)," ") | M12: =IFERROR( IF(AND(Table_Sales[[#This Row],[Revenue]]>0,Table_Sales[[#This Row],[Cost of Goods Sold]]>0), Table_Sales[[#This Row],[Revenue]]-Table_Sales[[#This Row],[Cost of Goods Sold]], ""), "")
D13: INV012 | G13: =_xlfn.XLOOKUP(Table_Sales[[#This Row],[Product Name]],Table6[Prodcuts],Table6[Product ID]," ") | K13: =IF(AND(Table_Sales[[#This Row],[Quantity Sold]]>0,Table_Sales[[#This Row],[Selling Price]]>0),Table_Sales[[#This Row],[Quantity Sold]]*Table_Sales[[#This Row],[Selling Price]]," ") | L13: =IF(AND(Table_Sales[[#This Row],[Quantity Sold]]>0,_xlfn.XLOOKUP(Table_Sales[[#This Row],[Product Name]],Inventory!D:D,Inventory!F:F)>0),I13*_xlfn.XLOOKUP(Table_Sales[[#This Row],[Product Name]],Inventory!D:D,Inventory!F:F)," ") | M13: =IFERROR( IF(AND(Table_Sales[[#This Row],[Revenue]]>0,Table_Sales[[#This Row],[Cost of Goods Sold]]>0), Table_Sales[[#This Row],[Revenue]]-Table_Sales[[#This Row],[Cost of Goods Sold]], ""), "")
D14: INV013 | G14: =_xlfn.XLOOKUP(Table_Sales[[#This Row],[Product Name]],Table6[Prodcuts],Table6[Product ID]," ") | K14: =IF(AND(Table_Sales[[#This Row],[Quantity Sold]]>0,Table_Sales[[#This Row],[Selling Price]]>0),Table_Sales[[#This Row],[Quantity Sold]]*Table_Sales[[#This Row],[Selling Price]]," ") | L14: =IF(AND(Table_Sales[[#This Row],[Quantity Sold]]>0,_xlfn.XLOOKUP(Table_Sales[[#This Row],[Product Name]],Inventory!D:D,Inventory!F:F)>0),I14*_xlfn.XLOOKUP(Table_Sales[[#This Row],[Product Name]],Inventory!D:D,Inventory!F:F)," ") | M14: =IFERROR( IF(AND(Table_Sales[[#This Row],[Revenue]]>0,Table_Sales[[#This Row],[Cost of Goods Sold]]>0), Table_Sales[[#This Row],[Revenue]]-Table_Sales[[#This Row],[Cost of Goods Sold]], ""), "")
... D201: INV200 | G201: =_xlfn.XLOOKUP(Table_Sales[[#This Row],[Product Name]],Table6[Prodcuts],Table6[Product ID]," ") | K201: =IF(AND(Table_Sales[[#This Row],[Quantity Sold]]>0,Table_Sales[[#This Row],[Selling Price]]>0),Table_Sales[[#This Row],[Quantity Sold]]*Table_Sales[[#This Row],[Selling Price]]," ") | L201: =IF(AND(Table_Sales[[#This Row],[Quantity Sold]]>0,_xlfn.XLOOKUP(Table_Sales[[#This Row],[Product Name]],Inventory!D:D,Inventory!F:F)>0),I201*_xlfn.XLOOKUP(Table_Sales[[#This Row],[Product Name]],Inventory!D:D,Inventory!F:F)," ") | M201: =IFERROR( IF(AND(Table_Sales[[#This Row],[Revenue]]>0,Table_Sales[[#This Row],[Cost of Goods Sold]]>0), Table_Sales[[#This Row],[Revenue]]-Table_Sales[[#This Row],[Cost of Goods Sold]], ""), "")

Sheet Operating Expenses
C1: Date | D1: Expense Category | E1: Description | F1: Amount
C2: 01/07/2026 | D2: Lunch | E2: Having lunch together | F2: 250

Sheet Customer Summary
C1: Customer Name | D1: Phone Number | E1: Number of Purchases | F1: Total Revenue Generated
C2: Rahim | D2: 017XXXXXXXX | E2: =COUNTIF(Sales!E:E,C2) -> 1 | F2: =SUMIF(Sales!E:E,C2,Sales!K:K) -> 2100

Sheet CodeKey
E6: Letter | F6: Number
E7: R | F7: 0
E8: S | F8: 1
E9: G | F9: 2
E10: H | F10: 3
E11: I | F11: 4
E12: J | F12: 5
E13: K | F13: 6
E14: l | F14: 7
E15: M | F15: 8
E16: N | F16: 9
